lib/__init__.py
lib01-1.0.0.dist-info/METADATA
lib01-1.0.0.dist-info/WHEEL
lib01-1.0.0.dist-info/top_level.txt
lib01-1.0.0.dist-info/RECORD
