Metadata-Version: 2.4
Name: lib01
Version: 1.0.0
Summary: Short description when they search in pip
Author: artitw
Author-email: XXXXXXXXX@gmail.com
Requires-Dist: requests
Dynamic: author
Dynamic: author-email
Dynamic: requires-dist
Dynamic: summary
